terraply/__init__.py
terraply/terraply.py
terraply-0.0.2.dist-info/LICENSE
terraply-0.0.2.dist-info/METADATA
terraply-0.0.2.dist-info/WHEEL
terraply-0.0.2.dist-info/entry_points.txt
terraply-0.0.2.dist-info/top_level.txt
terraply-0.0.2.dist-info/RECORD
