Metadata-Version: 2.1
Name: terraply
Version: 0.0.2
Summary: A wrapper to expand and exclude targets in terraform.
Author-email: Joshua Adkins <josh@nline.io>
Project-URL: Homepage, https://github.com/nline/terraply
Classifier: Programming Language :: Python :: 3
Classifier: License :: OSI Approved :: MIT License
Requires-Python: >=3.7
License-File: LICENSE
